py_crossbeam_channel-0.1.1.dist-info/METADATA
py_crossbeam_channel-0.1.1.dist-info/WHEEL
py_crossbeam_channel.cpython-38-darwin.so
py_crossbeam_channel-0.1.1.dist-info/RECORD
