Metadata-Version: 2.1
Name: py-crossbeam-channel
Version: 0.1.1
Summary: Python bindings to crossbeam-channel, providing the same API as the standard library's `queue.SimpleQueue`, but with support for backpressure
Author: Noé Rubinstein <noe.rubinstein@gmail.com>
Author-Email: Noé Rubinstein <noe.rubinstein@gmail.com>
